fpm/__init__.py
fpm/metadata/__init__.py
fpm/metadata/models.py
fpm_metadata-0.2.2.dist-info/LICENSE
fpm_metadata-0.2.2.dist-info/METADATA
fpm_metadata-0.2.2.dist-info/WHEEL
fpm_metadata-0.2.2.dist-info/top_level.txt
fpm_metadata-0.2.2.dist-info/RECORD
