Metadata-Version: 2.1
Name: fpm-metadata
Version: 0.2.2
Summary: Python model for the Fortran package manifest
Home-page: https://github.com/fortran-lang/fpm-metadata
Author: Sebastian Ehlert
Author-email: awvwgk@gmail.com
License: Apache-2.0
Classifier: Intended Audience :: Developers
Classifier: Operating System :: OS Independent
Classifier: Programming Language :: Python :: 3 :: Only
Classifier: Programming Language :: Python :: 3
Classifier: Programming Language :: Python :: 3.6
Classifier: Programming Language :: Python :: 3.7
Classifier: Programming Language :: Python :: 3.8
Classifier: Programming Language :: Python :: 3.9
Classifier: Programming Language :: Python :: 3.10
Requires-Python: >=3.6
License-File: LICENSE
Requires-Dist: pydantic
